hello_shinyerang-0.1.0.dist-info/METADATA
hello_shinyerang-0.1.0.dist-info/WHEEL
hello_shinyerang/__init__.py
hello_shinyerang-0.1.0.dist-info/RECORD
